dtpydb/__init__.py
dtpydb/config.py
dtpydb/database.py
dtpydb/health.py
dtpydb/model.py
dtpydb/search.py
dtpydb/utilities.py
dtpydb-1.0.8.dist-info/METADATA
dtpydb-1.0.8.dist-info/WHEEL
dtpydb-1.0.8.dist-info/RECORD
