Metadata-Version: 2.3
Name: dtpydb
Version: 1.0.8
Summary: A Python package for managing database connections, sessions, and ORM operations using SQLAlchemy. This package supports both synchronous and asynchronous database interactions with PostgreSQL.
License: MIT
Author: Reza Shirazi
Author-email: reza@datgate.com
Requires-Python: >=3.11.9,<3.12.0
Classifier: License :: OSI Approved :: MIT License
Classifier: Programming Language :: Python :: 3
Requires-Dist: SQLAlchemy (>=2.0.39,<2.1.0)
Requires-Dist: asyncpg (>=0.30.0,<0.31.0)
Requires-Dist: dtpyutils (>=1.0.0,<1.1.0)
Requires-Dist: psycopg2 (>=2.9.10,<2.10.0)
